subseqmodule/__init__.py
subseqmodule/subsequences.py
subseqmodule-0.1.0.dist-info/METADATA
subseqmodule-0.1.0.dist-info/WHEEL
subseqmodule-0.1.0.dist-info/top_level.txt
subseqmodule-0.1.0.dist-info/RECORD
