Metadata-Version: 2.4
Name: subseqmodule
Version: 0.1.0
Summary: Generate all subsequences of a list using recursion
Author-email: Gandla Abhinav <abhinavmails45@gmail.com>
Requires-Python: >=3.6
